README
graphitd
setup.py
graphit/__init__.py
graphit/client.py
graphit/server.py
graphit.egg-info/PKG-INFO
graphit.egg-info/SOURCES.txt
graphit.egg-info/dependency_links.txt
graphit.egg-info/requires.txt
graphit.egg-info/top_level.txt
watchers/graphit-disk
watchers/graphit-loadavg
watchers/graphit-mem
watchers/graphit-vnstat