Metadata-Version: 1.0
Name: graphit
Version: 0.6
Summary: A very simple server monitoring solution.
Home-page: http://idevelop.org/p/graphit
Author: Antoine Millet
Author-email: antoine@inaps.org
License: GPL3
Keywords: monitoring graph chart restful
Platform: UNKNOWN
Classifier: Development Status :: 4 - Beta
Classifier: Environment :: No Input/Output (Daemon)
Classifier: Intended Audience :: System Administrators
Classifier: Operating System :: OS Independent
Classifier: Programming Language :: Python :: 2.6
Classifier: Topic :: System :: Monitoring
Classifier: Topic :: System :: Networking :: Monitoring
Classifier: Topic :: Utilities
Classifier: License :: OSI Approved :: GNU General Public License (GPL)
